aipaze/__init__.py
aipaze/adapters.py
aipaze/client.py
aipaze/memory.py
aipaze/metrics.py
aipaze/middleware.py
aipaze/prompt_templates.py
aipaze/resources.py
aipaze/server.py
aipaze/tools.py
aipaze/utils.py
aipaze/validation.py
aipaze/vector_store.py
aipaze/workflow.py
aipaze-0.1.0.dist-info/METADATA
aipaze-0.1.0.dist-info/WHEEL
aipaze-0.1.0.dist-info/licenses/LICENSE
aipaze-0.1.0.dist-info/RECORD
