Metadata-Version: 2.4
Name: aipaze
Version: 0.1.0
Summary: A framework for connecting LLMs to external tools and data sources
Author-email: Vishal Singh Baraiya <realvixhal@gmail.com>
License-Expression: MIT
License-File: LICENSE
Keywords: ai,api,artificial intelligence,data,framework,llm,server,tools
Classifier: License :: OSI Approved :: MIT License
Classifier: Operating System :: OS Independent
Classifier: Programming Language :: Python :: 3
Requires-Python: >=3.8
Requires-Dist: aiohttp
Requires-Dist: black
Requires-Dist: faiss-cpu
Requires-Dist: flake8
Requires-Dist: huggingface
Requires-Dist: mypy
Requires-Dist: numpy
Requires-Dist: openai
Requires-Dist: pydantic
Requires-Dist: pytest
Requires-Dist: requests
Requires-Dist: sentence-transformers
Requires-Dist: transformers
Requires-Dist: websockets
